ipsdk/__init__.py
ipsdk/connection.py
ipsdk/exceptions.py
ipsdk/gateway.py
ipsdk/heuristics.py
ipsdk/http.py
ipsdk/jsonutils.py
ipsdk/logging.py
ipsdk/metadata.py
ipsdk/platform.py
ipsdk-0.7.0.dist-info/METADATA
ipsdk-0.7.0.dist-info/WHEEL
ipsdk-0.7.0.dist-info/licenses/LICENSE
ipsdk-0.7.0.dist-info/licenses/LICENSES.md
ipsdk-0.7.0.dist-info/RECORD
