Metadata-Version: 2.4
Name: ipsdk
Version: 0.7.0
Summary: Itential Python SDK
Project-URL: Homepage, https://itential.com
Project-URL: Repository, https://github.com/itential/ipsdk
Project-URL: Documentation, https://github.com/itential/ipsdk
Author-email: Itential <opensource@itential.com>
License: GPL-3.0-or-later
License-File: LICENSE
License-File: LICENSES.md
Keywords: api,automation,gateway,itential,platform,rest
Classifier: Development Status :: 4 - Beta
Classifier: Intended Audience :: Developers
Classifier: License :: OSI Approved :: GNU General Public License v3 or later (GPLv3+)
Classifier: Programming Language :: Python :: 3.10
Classifier: Programming Language :: Python :: 3.11
Classifier: Programming Language :: Python :: 3.12
Classifier: Topic :: Software Development :: Libraries
Classifier: Typing :: Typed
Requires-Python: >=3.10
Requires-Dist: httpx>=0.28.1
